pys/__init__.py
pys/base.py
pys/file.py
pys/pydantic.py
pys/sqlite.py
pys/zipfile.py
pysdato-0.0.14.dist-info/licenses/LICENSE
pysdato-0.0.14.dist-info/METADATA
pysdato-0.0.14.dist-info/WHEEL
pysdato-0.0.14.dist-info/top_level.txt
pysdato-0.0.14.dist-info/RECORD
