Metadata-Version: 2.4
Name: pysdato
Version: 0.0.14
Summary: Simple JSON file storage for Python dataclasses, msgspec structs and pydantic models, thread and multiprocess safe
Home-page: https://github.com/stasdavydov/pys
Author: Stas Davydov
Author-email: davidovsv@yandex.ru
License: MIT
Classifier: Development Status :: 5 - Production/Stable
Classifier: License :: OSI Approved :: MIT License
Classifier: Operating System :: OS Independent
Classifier: Intended Audience :: Developers
Classifier: Programming Language :: Python :: 3
Classifier: Programming Language :: Python :: 3.9
Classifier: Programming Language :: Python :: 3.10
Classifier: Programming Language :: Python :: 3.11
Classifier: Programming Language :: Python :: 3.12
Classifier: Programming Language :: Python :: 3.13
Classifier: Topic :: Database :: Database Engines/Servers
Classifier: Topic :: Software Development :: Libraries
Classifier: Topic :: Software Development :: Libraries :: Python Modules
Requires-Python: >=3.9
License-File: LICENSE
Requires-Dist: filelock>=3.19.1
Requires-Dist: msgspec>=0.19.0
Requires-Dist: zipremove>=0.8.0
Provides-Extra: test
Requires-Dist: pytest>=8.4.2; extra == "test"
Requires-Dist: msgspec>=0.19.0; extra == "test"
Requires-Dist: pydantic>=2.11.9; extra == "test"
Provides-Extra: dataclass
Requires-Dist: msgspec>=0.19.0; extra == "dataclass"
Provides-Extra: msgspec
Requires-Dist: msgspec>=0.19.0; extra == "msgspec"
Provides-Extra: pydantic
Requires-Dist: pydantic>=2.11.9; extra == "pydantic"
Dynamic: author
Dynamic: author-email
Dynamic: classifier
Dynamic: description
Dynamic: description-content-type
Dynamic: home-page
Dynamic: license
Dynamic: license-file
Dynamic: provides-extra
Dynamic: requires-dist
Dynamic: requires-python
Dynamic: summary
